austin_tools/__init__.py
austin_tools/public/__init__.py
austin_tools/public/datetimes.py
austin_tools/public/exceptional.py
austin_tools/public/public.py
austin_module_daily-0.0.6.dist-info/LICENSE.txt
austin_module_daily-0.0.6.dist-info/METADATA
austin_module_daily-0.0.6.dist-info/WHEEL
austin_module_daily-0.0.6.dist-info/top_level.txt
austin_module_daily-0.0.6.dist-info/RECORD
