Metadata-Version: 2.1
Name: austin-module-daily
Version: 0.0.6
Summary: Austin personally developed Python library.
Home-page: https://github.com/AustinFairyland/AustinModuleDaily
Author: Austin D
Author-email: fairylandhost@outlook.com
Classifier: Programming Language :: Python :: 3
Classifier: Natural Language :: English
Classifier: Natural Language :: Chinese (Simplified)
Classifier: Operating System :: Microsoft :: Windows :: Windows 11
Classifier: Topic :: Software Development :: Version Control :: Git
Classifier: License :: OSI Approved :: GNU Affero General Public License v3 or later (AGPLv3+)
Requires-Python: >=3.7
License-File: LICENSE.txt
